MANIFEST.in
README
setup.py
docs/README.rst
examples/ab.bnf
examples/base64.bnf
examples/class.bnf
examples/html.bnf
examples/http-post.bnf
examples/madlib.bnf
examples/slice.bnf
examples/strings.bnf
examples/upnp.bnf
nelly/__init__.py
nelly/dictionary.py
nelly/main.py
nelly/parser.py
nelly/program.py
nelly/rules.lex
nelly/sandbox.py
nelly/scanner.py
nelly/types.py
nelly/utils.py
nelly/version.py
nelly.egg-info/PKG-INFO
nelly.egg-info/SOURCES.txt
nelly.egg-info/dependency_links.txt
nelly.egg-info/entry_points.txt
nelly.egg-info/top_level.txt
nelly/grammars/constants.bnf
nelly/grammars/pack.bnf
nelly/grammars/common/datetime.bnf
nelly/grammars/compression/bzip2.bnf
nelly/grammars/compression/zlib.bnf
nelly/grammars/formats/wmf.bnf
nelly/grammars/formats/xml.bnf
nelly/grammars/protocols/dhcp.bnf
nelly/grammars/protocols/http.bnf
nelly/grammars/protocols/soap.bnf
nelly/grammars/protocols/upnp.bnf
nelly/grammars/ssl/cipher_suites.bnf
nelly/grammars/ssl/ssl.bnf