Metadata-Version: 1.1
Name: nelly
Version: 0.7.2
Summary: Python Test Case Generator
Home-page: https://github.com/moertle/nelly
Author: Matthew Shaw
Author-email: moertle@gmail.com
License: MIT
Platform: UNKNOWN
Classifier: Development Status :: 4 - Beta
Classifier: Intended Audience :: Developers
Classifier: License :: OSI Approved :: MIT License
Classifier: Topic :: Software Development :: Testing
Classifier: Programming Language :: Python :: 3
